README.rst
setup.cfg
setup.py
stackclimber.py
stackclimber.egg-info/PKG-INFO
stackclimber.egg-info/SOURCES.txt
stackclimber.egg-info/dependency_links.txt
stackclimber.egg-info/top_level.txt