Metadata-Version: 1.1
Name: stackclimber
Version: 0.99
Summary: Allow a function to discover the module or script name of its caller, or its caller's caller.
Home-page: https://github.com/drcloud/stackclimber
Author: Jason Dusek
Author-email: jason.dusek@gmail.com
License: UNKNOWN
Platform: UNKNOWN
Classifier: Environment :: Console
Classifier: Intended Audience :: Developers
Classifier: License :: OSI Approved :: MIT License
Classifier: Operating System :: Unix
Classifier: Operating System :: POSIX
Classifier: Programming Language :: Python
Classifier: Programming Language :: Python :: 2.6
Classifier: Programming Language :: Python :: 2.7
Classifier: Programming Language :: Python :: 3.5
Classifier: Topic :: Software Development
Classifier: Development Status :: 4 - Beta
